dkh_pixel/__init__.py
dkh_pixel-1.0.3.dist-info/LICENSE
dkh_pixel-1.0.3.dist-info/METADATA
dkh_pixel-1.0.3.dist-info/WHEEL
dkh_pixel-1.0.3.dist-info/top_level.txt
dkh_pixel-1.0.3.dist-info/RECORD
